sandbox/__init__.py
sandbox/db.sqlite3
sandbox/manage.py
sandbox/settings.py
sandbox/urls.py
sandbox/wsgi.py
sandbox/__pycache__/__init__.cpython-36.pyc
sandbox/__pycache__/__init__.cpython-37.pyc
sandbox/__pycache__/settings.cpython-36.pyc
sandbox/__pycache__/settings.cpython-37.pyc
sandbox/__pycache__/urls.cpython-36.pyc
sandbox/__pycache__/urls.cpython-37.pyc
sandbox/__pycache__/wsgi.cpython-36.pyc
sandbox/__pycache__/wsgi.cpython-37.pyc
sandbox/static/styles.css
sandbox/templates/registration/login.html
td_biblio/__init__.py
td_biblio/admin.py
td_biblio/apps.py
td_biblio/exceptions.py
td_biblio/factories.py
td_biblio/forms.py
td_biblio/models.py
td_biblio/urls.py
td_biblio/views.py
td_biblio/management/__init__.py
td_biblio/management/commands/__init__.py
td_biblio/management/commands/bibtex_import.py
td_biblio/migrations/0001_initial.py
td_biblio/migrations/0002_auto_20171201_1819.py
td_biblio/migrations/__init__.py
td_biblio/static/td_biblio/javascripts/td_biblio.js
td_biblio/templates/td_biblio/entry_import.html
td_biblio/templates/td_biblio/entry_item.html
td_biblio/templates/td_biblio/entry_list.html
td_biblio/templates/td_biblio/find_duplicated_authors.html
td_biblio/templates/td_biblio/bibliography_styles/ieeetr.html
td_biblio/templates/td_biblio/layouts/one_col.html
td_biblio/templates/td_biblio/layouts/sidebar_block.html
td_biblio/templates/td_biblio/layouts/three_cols.html
td_biblio/templates/td_biblio/layouts/two_cols_left_sidebar.html
td_biblio/templates/td_biblio/layouts/two_cols_right_sidebar.html
td_biblio/templates/td_biblio/partials/publication_list_by_year.html
td_biblio/templatetags/__init__.py
td_biblio/templatetags/td_biblio.py
td_biblio/tests/__init__.py
td_biblio/tests/conftest.py
td_biblio/tests/test_commands.py
td_biblio/tests/test_factories.py
td_biblio/tests/test_forms.py
td_biblio/tests/test_loaders.py
td_biblio/tests/test_models.py
td_biblio/tests/test_templatetags.py
td_biblio/tests/test_views.py
django_tailordev_biblio-2.0.0.dist-info/AUTHORS
django_tailordev_biblio-2.0.0.dist-info/LICENSE
django_tailordev_biblio-2.0.0.dist-info/METADATA
django_tailordev_biblio-2.0.0.dist-info/WHEEL
django_tailordev_biblio-2.0.0.dist-info/top_level.txt
django_tailordev_biblio-2.0.0.dist-info/RECORD
