Metadata-Version: 2.1
Name: django-tailordev-biblio
Version: 2.0.0
Summary: TailorDev Biblio  Bibliography management with Django.
Home-page: https://github.com/TailorDev/django-tailordev-biblio
Author: TailorDev
Author-email: hello+github@tailordev.fr
License: MIT
Keywords: django biblio bibliography bibtex publication
Platform: UNKNOWN
Classifier: Topic :: Internet :: WWW/HTTP :: Dynamic Content
Classifier: Intended Audience :: Developers
Classifier: Intended Audience :: Science/Research
Classifier: Intended Audience :: Information Technology
Classifier: Programming Language :: Python
Classifier: Programming Language :: Python :: 2
Classifier: Programming Language :: Python :: 2.7
Classifier: Programming Language :: Python :: 3
Classifier: Programming Language :: Python :: 3.4
Classifier: Programming Language :: Python :: 3.5
Classifier: Programming Language :: Python :: 3.6
Classifier: Programming Language :: Python :: 3.7
Classifier: Framework :: Django
Classifier: Framework :: Django :: 1.8
Classifier: Framework :: Django :: 1.9
Classifier: Framework :: Django :: 1.10
Classifier: Framework :: Django :: 1.11
Classifier: Framework :: Django :: 2.0
Classifier: Framework :: Django :: 2.1
Classifier: Development Status :: 5 - Production/Stable
Classifier: Operating System :: OS Independent
Requires-Dist: habanero (>=0.3.0)
Requires-Dist: Django (>=1.7)
Requires-Dist: eutils
Requires-Dist: bibtexparser
